py_iztro/__init__.py
py_iztro/core/__init__.py
py_iztro/core/astro.py
py_iztro/core/models.py
py_iztro/res/iztro-2.5.0.min.js
py_iztro-0.1.5.dist-info/METADATA
py_iztro-0.1.5.dist-info/WHEEL
py_iztro-0.1.5.dist-info/RECORD
