Metadata-Version: 2.4
Name: py-iztro
Version: 0.1.5
Summary: python 版iztro紫薇排盘工具
Project-URL: homepage, https://github.com/x-haose/py-iztro
Project-URL: repository, https://github.com/x-haose/py-iztro
Project-URL: documentation, https://github.com/x-haose/py-iztro
Author-email: 昊色居士 <xhrtxh@gmail.com>
Requires-Python: >=3.10
Requires-Dist: pydantic==2.10.6
Requires-Dist: pythonmonkey==1.1.0
